documentation/getting started.md
documentation/how_to_add_existing_tests_to_pipelines.md
documentation/how_to_design_new_tests.md
locaria_integrated_testing/__init__.py
locaria_integrated_testing/generic_tests/__init__.py
locaria_integrated_testing/generic_tests/data_quality_tests.py
locaria_integrated_testing/generic_tests/duplicate_tests.py
locaria_integrated_testing/generic_tests/freshness_tests.py
locaria_integrated_testing/generic_tests/row_count_tests.py
locaria_integrated_testing/main/acknowledge_manager.py
locaria_integrated_testing/main/testkit.py
locaria_integrated_testing/utils/config_manager.py
locaria_integrated_testing/utils/permission_resolver.py
locaria_integrated_testing-1.2.5.dist-info/METADATA
locaria_integrated_testing-1.2.5.dist-info/WHEEL
locaria_integrated_testing-1.2.5.dist-info/top_level.txt
locaria_integrated_testing-1.2.5.dist-info/RECORD
