Metadata-Version: 2.4
Name: locaria-integrated-testing
Version: 1.2.5
Summary: A lightweight, automated testing system for data pipelines and tools
Author: Locaria Data Team
License: MIT
Keywords: testing,data-quality,pipeline,validation
Classifier: Development Status :: 4 - Beta
Classifier: Intended Audience :: Developers
Classifier: License :: OSI Approved :: MIT License
Classifier: Programming Language :: Python :: 3
Classifier: Programming Language :: Python :: 3.8
Classifier: Programming Language :: Python :: 3.9
Classifier: Programming Language :: Python :: 3.10
Classifier: Programming Language :: Python :: 3.11
Requires-Python: >=3.8
Requires-Dist: google-cloud-bigquery>=3.0.0
Requires-Dist: google-cloud-firestore>=2.0.0
Requires-Dist: pandas>=1.3.0
Requires-Dist: requests>=2.25.0
Requires-Dist: protobuf<6.0.0,>=3.20.2
Provides-Extra: dev
Requires-Dist: pytest>=7.0.0; extra == "dev"
Requires-Dist: black>=22.0.0; extra == "dev"
Requires-Dist: flake8>=4.0.0; extra == "dev"
